moltree
molxvg
molparse/__init__.py
molparse/amber.py
molparse/amino.py
molparse/analysis.py
molparse/atom.py
molparse/atomtypes.py
molparse/bondlist.py
molparse/chain.py
molparse/compare.py
molparse/console_io.py
molparse/convert.py
molparse/go.py
molparse/graphing.py
molparse/group.py
molparse/gui.py
molparse/histidine.py
molparse/io.py
molparse/list.py
molparse/manipulate.py
molparse/ndx.py
molparse/network.py
molparse/ntp.py
molparse/nucleic.py
molparse/plot.py
molparse/povplot.py
molparse/protonate.py
molparse/py3d.py
molparse/residue.py
molparse/restraint.py
molparse/system.py
molparse/transform.py
molparse/tree.py
molparse/version.py
molparse/xvg.py
molparse/dl_poly/__init__.py
molparse/dl_poly/calculator.py
molparse/dl_poly/dl_poly_py.py
molparse/dna/__init__.py
molparse/dna/dna.py
molparse/hijack/__init__.py
molparse/hijack/hijack.py
molparse/monte/__init__.py
molparse/monte/carlo.py
molparse/monte/rand.py
molparse/monte/volumes.py
molparse/mutate/__init__.py
molparse/mutate/functional.py
molparse/mutate/link.py
molparse/mutate/protein.py
molparse/ndfes/__init__.py
molparse/ndfes/ndfes.py
molparse/rdkit/__init__.py
molparse/rdkit/classify.py
molparse/rdkit/compare.py
molparse/rdkit/draw.py
molparse/rdkit/features.py
molparse/rdkit/fingerprint.py
molparse/rdkit/mol.py
molparse/rdkit/sucos.py
molparse/rdkit/tools.py
molparse/rdkit/xca_utils.py
molparse/ref/ALA.pdb
molparse/ref/ARG.pdb
molparse/ref/ASN.pdb
molparse/ref/ASP.pdb
molparse/ref/AT_FLAT.pdb
molparse/ref/CYS.pdb
molparse/ref/GC_FLAT.pdb
molparse/ref/GLN.pdb
molparse/ref/GLU.pdb
molparse/ref/GLY.pdb
molparse/ref/HIS.pdb
molparse/ref/ILE.pdb
molparse/ref/LEU.pdb
molparse/ref/LYS.pdb
molparse/ref/MET.pdb
molparse/ref/PHE.pdb
molparse/ref/PRO.pdb
molparse/ref/SER.pdb
molparse/ref/THR.pdb
molparse/ref/TRP.pdb
molparse/ref/TYR.pdb
molparse/ref/VAL.pdb
molparse/signal/__init__.py
molparse/signal/fitwizard.py
molparse/signal/io.py
molparse/signal/modify.py
molparse/signal/peaks.py
molparse/sites/__init__.py
molparse-0.0.41.dist-info/METADATA
molparse-0.0.41.dist-info/WHEEL
molparse-0.0.41.dist-info/RECORD
