Metadata-Version: 2.4
Name: MolParse
Version: 0.0.41
Summary: Package for parsing, writing, and modifying molecular structure files
Project-URL: Homepage, https://molparse.winokan.com
Project-URL: Bug Tracker, https://github.com/mwinokan/MolParse/issues
Author-email: Max Winokan <max@winokan.com>
Classifier: License :: OSI Approved :: MIT License
Classifier: Operating System :: OS Independent
Classifier: Programming Language :: Python :: 3
Requires-Python: >=3.9
Requires-Dist: ase
Requires-Dist: ipython
Requires-Dist: kaleido
Requires-Dist: matplotlib
Requires-Dist: mpytools>=0.0.9
Requires-Dist: numpy
Requires-Dist: plotly
Requires-Dist: py3dmol
Requires-Dist: rdkit
